zapdos/__init__.py
zapdos/cli.py
zapdos/client.py
zapdos/definitions.py
zapdos/extract_frames.py
zapdos/video_indexer.py
zapdos/video_indexer_utils.py
zapdos_py-0.4.0.dist-info/licenses/LICENSE
zapdos_py-0.4.0.dist-info/METADATA
zapdos_py-0.4.0.dist-info/WHEEL
zapdos_py-0.4.0.dist-info/entry_points.txt
zapdos_py-0.4.0.dist-info/top_level.txt
zapdos_py-0.4.0.dist-info/RECORD
