Metadata-Version: 2.4
Name: zapdos-py
Version: 0.4.0
Summary: A CLI tool for indexing video files with programmatic access and enhanced events streaming
Author-email: Tri Nguyen <tri@zapdoslabs.com>
License-Expression: MIT
Keywords: cli,indexing,video,sdk,keyframes,events,streaming
Classifier: Development Status :: 3 - Alpha
Classifier: Intended Audience :: Developers
Classifier: Programming Language :: Python :: 3
Classifier: Programming Language :: Python :: 3.9
Classifier: Programming Language :: Python :: 3.10
Classifier: Programming Language :: Python :: 3.11
Classifier: Programming Language :: Python :: 3.12
Requires-Python: >=3.9
License-File: LICENSE
Requires-Dist: aiofiles>=24.1.0
Requires-Dist: aiohttp>=3.8.0
Requires-Dist: av>=15.0.0
Requires-Dist: jsonlines>=4.0.0
Requires-Dist: opencv-python>=4.12.0.88
Requires-Dist: requests>=2.28.0
Dynamic: license-file
